licenselynx/__init__.py
licenselynx/license_map.py
licenselynx/license_map_singleton.py
licenselynx/license_object.py
licenselynx/licenselynx.py
licenselynx/quotes_handler.py
licenselynx/resources/merged_data.json
licenselynx-2.0.1.dist-info/METADATA
licenselynx-2.0.1.dist-info/WHEEL
licenselynx-2.0.1.dist-info/licenses/LICENSE
licenselynx-2.0.1.dist-info/RECORD
