Metadata-Version: 2.4
Name: licenselynx
Version: 2.0.1
Summary: Unified License Mapper
License-Expression: BSD-3-Clause
License-File: LICENSE
Author: Leo Reinmann
Author-email: leo.reinmann@siemens.com
Requires-Python: >=3.11
Classifier: Programming Language :: Python :: 3
Classifier: Programming Language :: Python :: 3.11
Classifier: Programming Language :: Python :: 3.12
Classifier: Programming Language :: Python :: 3.13
Classifier: Programming Language :: Python :: 3.14
